TAN1_0/__init__.py
TAN1_0/main.py
TAN1-0.1.0.dist-info/METADATA
TAN1-0.1.0.dist-info/WHEEL
TAN1-0.1.0.dist-info/top_level.txt
TAN1-0.1.0.dist-info/RECORD
