Metadata-Version: 2.1
Name: TAN1
Version: 0.1.0
Summary: Python encryption by TAN binary
Author: TAN
Author-email: alfagartho@gmail.com
Classifier: Programming Language :: Python :: 3
Classifier: License :: OSI Approved :: MIT License
